prophet/serialize.py
prophet/plot.py
prophet/models.py
prophet/diagnostics.py
prophet/__init__.py
prophet/__version__.py
prophet/forecaster.py
prophet/utilities.py
prophet/make_holidays.py
prophet/stan_model/prophet.stan
prophet/stan_model/prophet
prophet/stan_model/prophet_model.bin
prophet/stan_model/cmdstan-2.37.0/bin/stansummary
prophet/stan_model/cmdstan-2.37.0/bin/diagnose
prophet/stan_model/cmdstan-2.37.0/bin/print
prophet/stan_model/cmdstan-2.37.0/bin/stanc
prophet/stan_model/cmdstan-2.37.0/stan/lib/stan_math/lib/tbb_2020.3/third-party-programs.txt
prophet/stan_model/cmdstan-2.37.0/stan/lib/stan_math/lib/tbb_2020.3/index.html
prophet/stan_model/cmdstan-2.37.0/stan/lib/stan_math/lib/tbb_2020.3/LICENSE
prophet/stan_model/cmdstan-2.37.0/stan/lib/stan_math/lib/tbb_2020.3/Makefile
prophet/stan_model/cmdstan-2.37.0/stan/lib/stan_math/lib/tbb_2020.3/CHANGES
prophet/stan_model/cmdstan-2.37.0/stan/lib/stan_math/lib/tbb_2020.3/STAN_CHANGES
prophet/stan_model/cmdstan-2.37.0/stan/lib/stan_math/lib/tbb_2020.3/README
prophet/stan_model/cmdstan-2.37.0/stan/lib/stan_math/lib/tbb_2020.3/README.md
prophet/stan_model/cmdstan-2.37.0/stan/lib/stan_math/lib/tbb_2020.3/.gitignore
prophet/stan_model/cmdstan-2.37.0/stan/lib/stan_math/lib/tbb_2020.3/.gitattributes
prophet/stan_model/cmdstan-2.37.0/stan/lib/stan_math/lib/tbb_2020.3/Doxyfile
prophet/stan_model/cmdstan-2.37.0/stan/lib/stan_math/lib/tbb_2020.3/cmake/TBBBuild.cmake
prophet/stan_model/cmdstan-2.37.0/stan/lib/stan_math/lib/tbb_2020.3/cmake/TBBInstallConfig.cmake
prophet/stan_model/cmdstan-2.37.0/stan/lib/stan_math/lib/tbb_2020.3/cmake/tbb_config_generator.cmake
prophet/stan_model/cmdstan-2.37.0/stan/lib/stan_math/lib/tbb_2020.3/cmake/tbb_config_installer.cmake
prophet/stan_model/cmdstan-2.37.0/stan/lib/stan_math/lib/tbb_2020.3/cmake/TBBMakeConfig.cmake
prophet/stan_model/cmdstan-2.37.0/stan/lib/stan_math/lib/tbb_2020.3/cmake/README.rst
prophet-1.2.0.dist-info/RECORD
prophet-1.2.0.dist-info/WHEEL
prophet-1.2.0.dist-info/top_level.txt
prophet-1.2.0.dist-info/METADATA
prophet-1.2.0.dist-info/licenses/LICENSE
